{
    "Changes": [
        {
            "LogName": "schedule.json: Medication Pick-ups (18th of Each Month)",
            "Action": "EditData",
            "Target": "Characters/schedules/{{Raven}}",
            "Entries": {
                "spring_18": "{{goToClinic}}/{{10am}} {{postClinic}}/{{goodNight}}",
                "summer_18": "{{goToClinic}}/{{10am}} {{postClinic}}/{{goodNight}}",
                "fall_18": "{{goToClinic}}/{{10am}} {{postClinic}}/{{goodNight}}",
                "winter_18": "{{goToClinic}}/{{10am}} {{postClinic}}/{{goodNight}}",
            },
        },
        {
            "LogName": "schedule.json: Festival Days",
            "Action": "EditData",
            "Target": "Characters/schedules/{{Raven}}",
            "Entries": {
                //Egg Festival: 9am - 2pm
                "spring_13": "{{goodMorningBus}}/{{910am}} {{relaxBushTown}}/{{210pm}} {{relaxBeach}}/{{goodNight}}",
                //Flower Dance: 9am - 2pm
                "spring_24": "{{goodMorningBus}}/{{910am}} {{standRiverForest}}/{{210pm}} {{standMountain}}/{{goodNight}}",
                //Luau: 9am - 2pm
                "summer_11": "{{goodMorningBus}}/{{910am}} {{relaxBeach}}/{{210pm}} {{standCC}}/{{goodNight}}",
                //Moonlight Jellies: 10pm - 12am
                "summer_28": "{{goodMorningBus}}/{{910am}} {{standStove}}/{{210pm}} {{standBookcase}}/{{8pm}} {{relaxBeach}}/{{1210am}} {{inBed}}",
                //Stardew Fair: 9am - 3pm
                "fall_16": "{{goodMorningBus}}/{{910am}} {{standCC}}/{{310pm}} {{standMountain}}/{{4pm}} {{standTableSaloon}}/{{goodNight}}",
                //Spirit's Eve: 10pm - 11:50pm
                "fall_27": "{{goodMorningBus}}/{{910am}} {{standStove}}/{{210pm}} {{standMountain}}/{{8pm}} {{relaxBushTown}}/{{1210am}} {{inBed}}",
                //Ice Festival: 9am - 2pm
                "winter_8": "{{goodMorningBus}}/{{910am}} {{standRiverForest}}/{{210pm}} {{relaxBushTown}}/{{5pm}} {{standCC}}/{{goodNight}}",
                //Winter Star: 9am - 2pm
                "winter_25": "{{goodMorningBus}}/{{910am}} {{relaxBushTown}}/{{210pm}} {{standRiverForest}}/{{goodNight}}",
            },
        },
        {
            "LogName": "schedule.json: General",
            "Action": "EditData",
            "Target": "Characters/schedules/{{Raven}}",
            "Entries": {
                "Mon": "{{workDay}}",
                "Tue": "{{freeDay}}",
                "Wed": "{{freeDay}}",
                "Thu": "{{freeDay}}",
                "Fri": "{{workDay}}",
                "Sat": "{{workDay}}",
                "Sun": "{{workDay}}",
                
                "spring": "{{goodMorning}}/{{inBed}}",
            },
        },
        {
            "LogName": "schedule.json: Marriage",
            "Action": "EditData",
            "Target": "Characters/schedules/{{Raven}}",
            "Entries": {
                //Medication Pick-Up
                "marriage_spring_18": "{{medsDay}}",
                "marriage_summer_18": "{{medsDay}}",
                "marriage_fall_18": "{{medsDay}}",
                "marriage_winter_18": "{{medsDay}}",

                //Marriage
                "marriage_Sat": "{{930am}} {{jobTasksSaloon}}/{{6pm}} bed",
                "marriage_Sun": "{{930am}} {{jobTasksSaloon}}/{{6pm}} bed",
            },
        },
    ]
}